shitposts/__init__.py
shitposts/errors.py
shitposts/session.py
shitposts-0.1.1.dist-info/LICENSE
shitposts-0.1.1.dist-info/METADATA
shitposts-0.1.1.dist-info/WHEEL
shitposts-0.1.1.dist-info/top_level.txt
shitposts-0.1.1.dist-info/RECORD
