Metadata-Version: 2.1
Name: shitposts
Version: 0.1.1
Summary: Asynchronous wrapper for ShitpostAPI.
Home-page: https://github.com/regulad/shitposts
Author: regulad
Author-email: regulad@outlook.com
License: GPLv3
Download-URL: https://codeload.github.com/regulad/shitposts/zip/refs/heads/main
Keywords: async,api
Platform: UNKNOWN
Classifier: Intended Audience :: Developers
Classifier: License :: OSI Approved :: GNU General Public License v3 (GPLv3)
Classifier: Programming Language :: Python :: 3
Classifier: Programming Language :: Python :: 3.6
Classifier: Programming Language :: Python :: 3.7
Classifier: Programming Language :: Python :: 3.8
Classifier: Programming Language :: Python :: 3.9
License-File: LICENSE
Requires-Dist: aiohttp
